LICENSE
MANIFEST.in
README.md
manage_lua_fastutils.py
requirements.txt
setup.py
lua_fastutils/__init__.py
lua_fastutils.egg-info/PKG-INFO
lua_fastutils.egg-info/SOURCES.txt
lua_fastutils.egg-info/dependency_links.txt
lua_fastutils.egg-info/entry_points.txt
lua_fastutils.egg-info/not-zip-safe
lua_fastutils.egg-info/requires.txt
lua_fastutils.egg-info/top_level.txt
lua_fastutils/src/.rockspec
lua_fastutils/src/lua/fastutils/httputils.lua
lua_fastutils/src/lua/fastutils/strutils.lua
lua_fastutils/src/lua/fastutils/tableutils.lua
lua_fastutils/src/lua/fastutils/typingutils.lua
lua_fastutils/src/lua/test/httputils.lua
lua_fastutils/src/lua/test/strutils.lua
lua_fastutils/src/lua/test/tableutils.lua
lua_fastutils/src/lua/test/typingutils.lua