Metadata-Version: 2.1
Name: lua-fastutils
Version: 0.1.8.1
Summary: Collection of simple utils.
Home-page: https://github.com/zencore-cn/zencore-issues
Author: zencore
Author-email: dobetter@zencore.cn
License: MIT
Platform: UNKNOWN
Classifier: Development Status :: 5 - Production/Stable
Classifier: Intended Audience :: Developers
Classifier: Topic :: Software Development :: Libraries :: Python Modules
Classifier: License :: OSI Approved :: MIT License
Classifier: Programming Language :: Python :: 3
Classifier: Programming Language :: Python :: 3 :: Only
